{
  "total_queries": 2,
  "internet_results": {
    "sentiment analysis tools features": {
      "query_id": 5,
      "status": "success",
      "query_type": "tools"
    },
    "best sentiment analysis software": {
      "query_id": 7,
      "status": "success",
      "query_type": "tools"
    }
  },
  "papers_results": {
    "sentiment analysis tools features": {
      "status": "failed",
      "query_type": "tools"
    },
    "best sentiment analysis software": {
      "status": "failed",
      "query_type": "tools"
    }
  },
  "errors": [],
  "start_time": "2025-06-06T16:22:45.804356",
  "topic": "sentiment analysis tools",
  "end_time": "2025-06-06T16:23:12.657056"
}